whinesnips/__init__.py
whinesnips/constants/const.mp
whinesnips/utils/__init__.py
whinesnips/utils/base_exc.py
whinesnips/utils/cfg.py
whinesnips/utils/exceptions.py
whinesnips/utils/types.py
whinesnips/utils/utils.py
whinesnips-0.0.0.0a4.dist-info/METADATA
whinesnips-0.0.0.0a4.dist-info/WHEEL
whinesnips-0.0.0.0a4.dist-info/RECORD
