Metadata-Version: 2.1
Name: whinesnips
Version: 0.0.0.0a4
Summary: None
Home-page: https://whsn.whinyaan.xyz
License: MIT
Keywords: your,keywords,here
Author: whitespace_negative
Author-email: whinyaan@protonmail.com
Maintainer: whitespace_negative
Maintainer-email: whinyaan@protonmail.com
Requires-Python: >=3.10,<4
Classifier: Development Status :: 2 - Pre-Alpha
Classifier: Environment :: Console
Classifier: Intended Audience :: Developers
Classifier: License :: OSI Approved :: MIT License
Classifier: Natural Language :: English
Classifier: Operating System :: OS Independent
Classifier: Programming Language :: Python :: 3
Classifier: Programming Language :: Python :: 3.10
Classifier: Programming Language :: Python :: 3.11
Classifier: Programming Language :: Python :: 3.12
Classifier: Topic :: Utilities
Requires-Dist: msgpack (>=1.0.5,<2.0.0)
Requires-Dist: pyyaml (>=6.0,<7.0)
Project-URL: Documentation, https://whsn.whinyaan.xyz
Project-URL: Repository, https://github.com/whinee/whinesnips
